one_public_api/__init__.py
one_public_api/common/__init__.py
one_public_api/common/constants.py
one_public_api/common/init_data.py
one_public_api/common/query_param.py
one_public_api/common/tools.py
one_public_api/common/utility/__init__.py
one_public_api/common/utility/files.py
one_public_api/common/utility/str.py
one_public_api/core/__init__.py
one_public_api/core/database.py
one_public_api/core/exceptions.py
one_public_api/core/extensions.py
one_public_api/core/i18n.py
one_public_api/core/log.py
one_public_api/core/py.typed
one_public_api/core/settings.py
one_public_api/crud/__init__.py
one_public_api/crud/data_creator.py
one_public_api/crud/data_deleter.py
one_public_api/crud/data_reader.py
one_public_api/crud/data_updater.py
one_public_api/locales/en/LC_MESSAGES/messages.mo
one_public_api/locales/en/LC_MESSAGES/messages.po
one_public_api/locales/ja/LC_MESSAGES/messages.mo
one_public_api/locales/ja/LC_MESSAGES/messages.po
one_public_api/locales/messages.pot
one_public_api/main.py
one_public_api/models/__init__.py
one_public_api/models/mixins/__init__.py
one_public_api/models/mixins/id_mixin.py
one_public_api/models/mixins/maintenance_mixin.py
one_public_api/models/mixins/password_mixin.py
one_public_api/models/mixins/timestamp_mixin.py
one_public_api/models/py.typed
one_public_api/models/system/__init__.py
one_public_api/models/system/configuration_model.py
one_public_api/models/system/feature_model.py
one_public_api/models/system/user_model.py
one_public_api/py.typed
one_public_api/routers/__init__.py
one_public_api/routers/authenticate_router.py
one_public_api/routers/base_route.py
one_public_api/routers/configuration_router.py
one_public_api/routers/feature_router.py
one_public_api/routers/user_router.py
one_public_api/schemas/__init__.py
one_public_api/schemas/authenticate_schema.py
one_public_api/schemas/configuration_schema.py
one_public_api/schemas/feature_schema.py
one_public_api/schemas/response_schema.py
one_public_api/schemas/user_schema.py
one_public_api-0.1.1a0.dist-info/METADATA
one_public_api-0.1.1a0.dist-info/WHEEL
one_public_api-0.1.1a0.dist-info/RECORD
