Metadata-Version: 2.3
Name: one-public-api
Version: 0.1.1a0
Summary: This package provides the API layer of the One Public Framework.
License: MIT License
Author: Roba
Author-email: roba@one-coder.com
Requires-Python: >=3.11,<4.0
Classifier: License :: Other/Proprietary License
Classifier: Programming Language :: Python :: 3
Classifier: Programming Language :: Python :: 3.11
Classifier: Programming Language :: Python :: 3.12
Classifier: Programming Language :: Python :: 3.13
Requires-Dist: bcrypt (>=4.0.1,<5.0.0)
Requires-Dist: fastapi (>=0.115.12,<0.116.0)
Requires-Dist: passlib[bcrypt] (>=1.7.4,<2.0.0)
Requires-Dist: psycopg2-binary (>=2.9.10,<3.0.0)
Requires-Dist: pydantic-settings (>=2.9.1,<3.0.0)
Requires-Dist: pydantic[email] (>=2.11.7,<3.0.0)
Requires-Dist: pyjwt (>=2.10.1,<3.0.0)
Requires-Dist: python-multipart (>=0.0.20,<0.0.21)
Requires-Dist: sqlmodel (>=0.0.24,<0.0.25)
Requires-Dist: uvicorn[standard] (>=0.34.3,<0.35.0)
